{
  "contractType": "TRIGGER_SMART_CONTRACT",
  "contractTypeNum": 31,
  "caseName": "storage_overwrite",
  "caseCategory": "happy",
  "description": "Overwrite existing storage slot with new value",
  "generatedAt": "2026-01-25T09:15:45.393Z",
  "generatorVersion": "1.0.0",
  "blockNumber": 0,
  "blockTimestamp": 0,
  "databasesTouched": [
    "account",
    "contract",
    "code",
    "abi",
    "contract-state",
    "dynamic-properties"
  ],
  "expectedStatus": "SUCCESS",
  "ownerAddress": "a0abd4b9367799eaa3197fecb144eb71de1e049abc",
  "dynamicProperties": {},
  "notes": []
}